archliner/__init__.py
archliner/__main__.py
archliner/core.py
archliner-0.1.0.dist-info/METADATA
archliner-0.1.0.dist-info/WHEEL
archliner-0.1.0.dist-info/entry_points.txt
archliner-0.1.0.dist-info/licenses/LICENSE
archliner-0.1.0.dist-info/RECORD
