Metadata-Version: 2.4
Name: archliner
Version: 0.1.0
Summary: A fast, Python-based launcher for Arch Linux & XFCE.
Author-email: gnakw <gnakw@outlook.com>
License-File: LICENSE
Requires-Python: >=3.11
Requires-Dist: pyside6>=6.10.1
